dialer/__init__.py
dialer/configs/__init__.py
dialer/configs/logger.py
dialer/configs/settings.py
dialer/database/__init__.py
dialer/database/crud_ops.py
dialer/database/database.sample.ini
dialer/database/dbwork.py
dialer/database/models.py
dialer/handlers/__init__.py
dialer/handlers/files.py
dialer/scripts/__init__.py
dialer/scripts/calllogic.py
dialer/scripts/post_install.py
dialer/scripts/post_install.sh
dialer/scripts/upload.py
dialer-0.2.5.dist-info/METADATA
dialer-0.2.5.dist-info/WHEEL
dialer-0.2.5.dist-info/entry_points.txt
dialer-0.2.5.dist-info/RECORD
