Metadata-Version: 2.1
Name: dialer
Version: 0.2.5
Summary: Automate customer trainings over the phone with no human intervention.
Home-page: https://github.com/nelsonk/dialer
Author: Nelson Kanyali
Author-email: nelskon@gmail.com
Requires-Python: >=3.7
Classifier: Programming Language :: Python :: 3
Classifier: Programming Language :: Python :: 3.7
Classifier: Programming Language :: Python :: 3.8
Classifier: Programming Language :: Python :: 3.9
Classifier: Programming Language :: Python :: 3.10
Classifier: Programming Language :: Python :: 3.11
Classifier: Programming Language :: Python :: 3.12
Requires-Dist: peewee
Requires-Dist: pymysql (>=1.1.1)
Project-URL: Repository, https://github.com/nelsonk/dialer
